ann3/__init__.py
ann3/nn.py
ann3-0.1.dist-info/LICENSE
ann3-0.1.dist-info/METADATA
ann3-0.1.dist-info/WHEEL
ann3-0.1.dist-info/top_level.txt
ann3-0.1.dist-info/RECORD
