Metadata-Version: 2.1
Name: ann3
Version: 0.1
Summary: A simple neural network implementation
Home-page: https://github.com/yourusername/mllab4
Author: wanderer22
Author-email: wanderingwolves22@gmail.com
License: UNKNOWN
Platform: UNKNOWN
Classifier: Programming Language :: Python :: 3
Classifier: License :: OSI Approved :: MIT License
Classifier: Operating System :: OS Independent
License-File: LICENSE
Requires-Dist: numpy
